brilliance_admin/__init__.py
brilliance_admin/auth.py
brilliance_admin/docs.py
brilliance_admin/exceptions.py
brilliance_admin/translations.py
brilliance_admin/utils.py
brilliance_admin/api/__init__.py
brilliance_admin/api/routers.py
brilliance_admin/api/utils.py
brilliance_admin/api/views/__init__.py
brilliance_admin/api/views/auth.py
brilliance_admin/api/views/autocomplete.py
brilliance_admin/api/views/dashboard.py
brilliance_admin/api/views/index.py
brilliance_admin/api/views/schema.py
brilliance_admin/api/views/settings.py
brilliance_admin/api/views/table.py
brilliance_admin/integrations/__init__.py
brilliance_admin/integrations/sqlalchemy/__init__.py
brilliance_admin/integrations/sqlalchemy/auth.py
brilliance_admin/integrations/sqlalchemy/autocomplete.py
brilliance_admin/integrations/sqlalchemy/fields.py
brilliance_admin/integrations/sqlalchemy/fields_schema.py
brilliance_admin/integrations/sqlalchemy/table/__init__.py
brilliance_admin/integrations/sqlalchemy/table/base.py
brilliance_admin/integrations/sqlalchemy/table/create.py
brilliance_admin/integrations/sqlalchemy/table/delete.py
brilliance_admin/integrations/sqlalchemy/table/list.py
brilliance_admin/integrations/sqlalchemy/table/retrieve.py
brilliance_admin/integrations/sqlalchemy/table/update.py
brilliance_admin/locales/en.yml
brilliance_admin/locales/ru.yml
brilliance_admin/schema/__init__.py
brilliance_admin/schema/admin_schema.py
brilliance_admin/schema/category.py
brilliance_admin/schema/dashboard/__init__.py
brilliance_admin/schema/dashboard/category_dashboard.py
brilliance_admin/schema/table/__init__.py
brilliance_admin/schema/table/admin_action.py
brilliance_admin/schema/table/category_table.py
brilliance_admin/schema/table/fields_schema.py
brilliance_admin/schema/table/table_models.py
brilliance_admin/schema/table/fields/__init__.py
brilliance_admin/schema/table/fields/base.py
brilliance_admin/schema/table/fields/function_field.py
brilliance_admin/static/index-B8JOx1Ps.css
brilliance_admin-0.44.13.dist-info/licenses/LICENSE
brilliance_admin-0.44.13.dist-info/METADATA
brilliance_admin-0.44.13.dist-info/WHEEL
brilliance_admin-0.44.13.dist-info/top_level.txt
brilliance_admin-0.44.13.dist-info/RECORD
