Metadata-Version: 2.4
Name: brilliance-admin
Version: 0.44.13
Summary: Simple and lightweight data managment framework powered by FastAPI and Vue3 Vuetify all-in-one. Some call it heavenly in its brilliance.
License-Expression: MIT
Requires-Python: >=3.10
License-File: LICENSE
Requires-Dist: asgiref>=3.11
Requires-Dist: fastapi>=0.115
Requires-Dist: jinja2>=3.1
Requires-Dist: PyYAML>=6.0
Provides-Extra: example
Requires-Dist: uvicorn>=0.34.0; extra == "example"
Requires-Dist: faker>=38.2.0; extra == "example"
Requires-Dist: pyjwt>=2.10.1; extra == "example"
Requires-Dist: structlog>=25.5.0; extra == "example"
Requires-Dist: rich>=14.2.0; extra == "example"
Requires-Dist: asyncpg>=0.31.0; extra == "example"
Requires-Dist: pydantic-settings>=2.12.0; extra == "example"
Requires-Dist: twine; extra == "example"
Provides-Extra: tests
Requires-Dist: pytest>=8.4.2; extra == "tests"
Requires-Dist: pytest-asyncio>=1.2.0; extra == "tests"
Requires-Dist: httpx>=0.28.1; extra == "tests"
Requires-Dist: pytest-mock>=3.15.1; extra == "tests"
Requires-Dist: sqlalchemy>=2.0.41; extra == "tests"
Requires-Dist: aiosqlite>=0.22.1; extra == "tests"
Requires-Dist: factory-boy>=3.3.3; extra == "tests"
Requires-Dist: pyjwt>=2.10.1; extra == "tests"
Provides-Extra: scalar
Requires-Dist: scalar-fastapi>=1.5.0; extra == "scalar"
Dynamic: license-file
